LICENSE
README.rst
setup.py
bson/__init__.py
bson/_cbsonmodule.c
bson/_helpers.py
bson/binary.py
bson/buffer.c
bson/code.py
bson/codec_options.py
bson/codec_options.pyi
bson/dbref.py
bson/decimal128.py
bson/errors.py
bson/int64.py
bson/json_util.py
bson/max_key.py
bson/min_key.py
bson/objectid.py
bson/py.typed
bson/raw_bson.py
bson/regex.py
bson/son.py
bson/time64.c
bson/timestamp.py
bson/tz_util.py
gridfs/__init__.py
gridfs/errors.py
gridfs/grid_file.py
gridfs/py.typed
pymongo/__init__.py
pymongo/_cmessagemodule.c
pymongo/_csot.py
pymongo/aggregation.py
pymongo/auth.py
pymongo/auth_aws.py
pymongo/bulk.py
pymongo/change_stream.py
pymongo/client_options.py
pymongo/client_session.py
pymongo/collation.py
pymongo/collection.py
pymongo/command_cursor.py
pymongo/common.py
pymongo/compression_support.py
pymongo/cursor.py
pymongo/daemon.py
pymongo/database.py
pymongo/driver_info.py
pymongo/encryption.py
pymongo/encryption_options.py
pymongo/errors.py
pymongo/event_loggers.py
pymongo/hello.py
pymongo/helpers.py
pymongo/max_staleness_selectors.py
pymongo/message.py
pymongo/mongo_client.py
pymongo/monitor.py
pymongo/monitoring.py
pymongo/network.py
pymongo/ocsp_cache.py
pymongo/ocsp_support.py
pymongo/operations.py
pymongo/periodic_executor.py
pymongo/pool.py
pymongo/py.typed
pymongo/pyopenssl_context.py
pymongo/read_concern.py
pymongo/read_preferences.py
pymongo/response.py
pymongo/results.py
pymongo/saslprep.py
pymongo/server.py
pymongo/server_api.py
pymongo/server_description.py
pymongo/server_selectors.py
pymongo/server_type.py
pymongo/settings.py
pymongo/socket_checker.py
pymongo/srv_resolver.py
pymongo/ssl_context.py
pymongo/ssl_support.py
pymongo/topology.py
pymongo/topology_description.py
pymongo/typings.py
pymongo/uri_parser.py
pymongo/write_concern.py
python_mong0.egg-info/PKG-INFO
python_mong0.egg-info/SOURCES.txt
python_mong0.egg-info/dependency_links.txt
python_mong0.egg-info/requires.txt
python_mong0.egg-info/top_level.txt
test/test_auth.py
test/test_auth_spec.py
test/test_binary.py
test/test_bson.py
test/test_bson_corpus.py
test/test_bulk.py
test/test_change_stream.py
test/test_client.py
test/test_client_context.py
test/test_cmap.py
