Metadata-Version: 2.1
Name: python-mong0
Version: 4.2.0
Summary: Python driver for MongoDB <http://www.mongodb.org>
Home-page: http://github.com/mongodb/mongo-python-driver
Author: The MongoDB Python Team
License: Apache License, Version 2.0
Keywords: mongo,mongodb,pymongo,gridfs,bson
Platform: UNKNOWN
Classifier: Development Status :: 5 - Production/Stable
Classifier: Intended Audience :: Developers
Classifier: License :: OSI Approved :: Apache Software License
Classifier: Operating System :: MacOS :: MacOS X
Classifier: Operating System :: Microsoft :: Windows
Classifier: Operating System :: POSIX
Classifier: Programming Language :: Python :: 3
Classifier: Programming Language :: Python :: 3 :: Only
Classifier: Programming Language :: Python :: 3.7
Classifier: Programming Language :: Python :: 3.8
Classifier: Programming Language :: Python :: 3.9
Classifier: Programming Language :: Python :: 3.10
Classifier: Programming Language :: Python :: Implementation :: CPython
Classifier: Programming Language :: Python :: Implementation :: PyPy
Classifier: Topic :: Database
Classifier: Typing :: Typed
Requires-Python: >=3.7
Provides-Extra: encryption
Provides-Extra: ocsp
Provides-Extra: snappy
Provides-Extra: zstd
Provides-Extra: aws
Provides-Extra: srv
Provides-Extra: gssapi
License-File: LICENSE
